cals/__init__.py
cals/birashk.py
cals/core.py
cals/data.py
cals/gregorian.py
cals/official.py
cals/utils.py
cals-0.1.0.dist-info/LICENSE.txt
cals-0.1.0.dist-info/METADATA
cals-0.1.0.dist-info/WHEEL
cals-0.1.0.dist-info/top_level.txt
cals-0.1.0.dist-info/RECORD
