Metadata-Version: 2.1
Name: cals
Version: 0.1.0
Summary: A python package for calendrical calculations
Home-page: https://github.com/behrouzz/cals
Author: Behrouz Safari
Author-email: behrouz.safari@gmail.com
License: MIT
Classifier: Programming Language :: Python :: 3
Classifier: License :: OSI Approved :: MIT License
Classifier: Operating System :: OS Independent
Requires-Python: >=3.6
License-File: LICENSE.txt
Requires-Dist: numpy
Requires-Dist: scipy
Requires-Dist: pandas
Requires-Dist: requests
